atelierflow/__init__.py
atelierflow/experiment.py
atelierflow/core/__init__.py
atelierflow/core/metric.py
atelierflow/core/model.py
atelierflow/core/step.py
atelierflow/core/step_result.py
atelierflow/steps/__init__.py
atelierflow/steps/common/save_data/save_to_avro.py
atelierflow-0.1.1.dist-info/licenses/LICENSE
atelierflow-0.1.1.dist-info/METADATA
atelierflow-0.1.1.dist-info/WHEEL
atelierflow-0.1.1.dist-info/top_level.txt
atelierflow-0.1.1.dist-info/RECORD
