Metadata-Version: 2.4
Name: atelierflow
Version: 0.1.1
Summary: A lightweight Python framework for creating clear, reproducible, and scalable machine learning pipelines.
Author-email: Marcelo Brito <mhbcoelho99@gmail.com>
License: MIT License
Project-URL: Homepage, https://github.com/IoTDataAtelier/pipeflow
Keywords: mlops,pipeline,machine-learning,orchestration,reproducibility
Classifier: Programming Language :: Python :: 3
Classifier: License :: OSI Approved :: MIT License
Classifier: Operating System :: OS Independent
Requires-Python: >=3.9
License-File: LICENSE
Requires-Dist: pandas
Requires-Dist: fastavro
Provides-Extra: torch
Requires-Dist: torch; extra == "torch"
Provides-Extra: sklearn
Requires-Dist: scikit-learn; extra == "sklearn"
Provides-Extra: tensorflow
Requires-Dist: tensorflow; extra == "tensorflow"
Provides-Extra: all
Requires-Dist: atelierflow[torch]; extra == "all"
Requires-Dist: atelierflow[sklearn]; extra == "all"
Requires-Dist: atelierflow[tensorflow]; extra == "all"
Dynamic: license-file
